majormode/__init__.py
majormode/utils/__init__.py
majormode/utils/namegen.py
majormode/utils/languages/beowulf.txt
majormode/utils/languages/celticmyth.txt
majormode/utils/languages/elven.txt
majormode/utils/languages/greek.txt
majormode/utils/languages/greek2.txt
majormode/utils/languages/hebrew.txt
majormode/utils/languages/hebrew2.txt
majormode/utils/languages/japanese.txt
majormode/utils/languages/japanese2.txt
majormode/utils/languages/lusiadas.txt
majormode/utils/languages/lusiadas2.txt
majormode/utils/languages/norse.txt
majormode/utils/languages/norsemyth.txt
majormode/utils/languages/odin.txt
majormode/utils/languages/polish.txt
majormode/utils/languages/polish2.txt
majormode/utils/languages/roman.txt
majormode/utils/languages/russian.txt
majormode/utils/languages/saxon.txt
majormode/utils/languages/welsh.txt
perseus_name_generator_library-1.1.0.dist-info/LICENSE
perseus_name_generator_library-1.1.0.dist-info/METADATA
perseus_name_generator_library-1.1.0.dist-info/WHEEL
perseus_name_generator_library-1.1.0.dist-info/top_level.txt
perseus_name_generator_library-1.1.0.dist-info/RECORD
