Metadata-Version: 2.1
Name: perseus-name-generator-library
Version: 1.1.0
Summary: Reusable Python components to be shared with some Python projects
Home-page: https://github.com/dcaune/perseus-name-generator-python-library
Author: Daniel CAUNE
Author-email: daniel.caune@gmail.com
License: MIT
Project-URL: Bug Tracker, https://github.com/dcaune/perseus-name-generator-python-library/issues
Project-URL: Documentation, https://github.com/dcaune/perseus-name-generator-python-library
Project-URL: Source Code, https://github.com/dcaune/perseus-name-generator-python-library
Platform: any
Classifier: Development Status :: 5 - Production/Stable
Classifier: License :: OSI Approved :: MIT License
Classifier: Operating System :: OS Independent
Classifier: Programming Language :: Python
Classifier: Topic :: Software Development :: Libraries
Requires-Dist: pipfile
Requires-Dist: perseus-core-library
